MANIFEST.in
README.md
setup.cfg
setup.py
dong/__init__.py
dong/auth.py
dong/cliapp.py
dong/decorators.py
dong/httpclient.py
dong/net.py
dong/project.py
dong/structure.py
dong/utils.py
dong.egg-info/PKG-INFO
dong.egg-info/SOURCES.txt
dong.egg-info/dependency_links.txt
dong.egg-info/entry_points.txt
dong.egg-info/not-zip-safe
dong.egg-info/requires.txt
dong.egg-info/top_level.txt
dong/commands/__init__.py
dong/commands/cmd_auth.py
dong/commands/cmd_data.py
dong/commands/cmd_endpoint.py
dong/commands/cmd_help.py
dong/commands/cmd_init.py
dong/commands/cmd_local.py
dong/commands/cmd_login.py
dong/commands/cmd_model.py
dong/commands/cmd_new.py
dong/commands/cmd_template.py
dong/commands/cmd_train.py
dong/commands/cmd_version.py
dong/framework/__init__.py
dong/templates/__init__.py
dong/templates/__init__.template
dong/templates/config.template
dong/templates/data.template
dong/templates/endpoint.template
dong/templates/manifest_in.template
dong/templates/model.template
dong/templates/save_load.template
dong/templates/service.template
dong/templates/setup_py.template
dong/templates/train.template
dong/templates/train__init__.template
dong/templates/train_json.template
dong/templates/tune.template
dong/templates/tune__init__.template
dong/templates/model/init.template
dong/templates/model/serializer.template
dong/templates/model/train.template
dong/templates/model/update.template