Metadata-Version: 2.1
Name: dong
Version: 0.2.1.8
Summary: Universal Command Line Interface for Libgirl AI Platform
Home-page: https://dong.libgirl.com/
Author: Team Libgirl
Author-email: team@libgirl.com
License: Apache License 2.0
Platform: UNKNOWN
